LICENSE.txt
MANIFEST.in
README.md
setup.py
pyGPUreg/__init__.py
pyGPUreg/opengl_classes.py
pyGPUreg/pyGPUreg.py
pyGPUreg.egg-info/PKG-INFO
pyGPUreg.egg-info/SOURCES.txt
pyGPUreg.egg-info/dependency_links.txt
pyGPUreg.egg-info/requires.txt
pyGPUreg.egg-info/top_level.txt
pyGPUreg/shaders/butterflytexture.glsl
pyGPUreg/shaders/copy_r_to_rg.glsl
pyGPUreg/shaders/cos_filter.glsl
pyGPUreg/shaders/cos_filter_r.glsl
pyGPUreg/shaders/fft.glsl
pyGPUreg/shaders/fft_inversion_permutation.glsl
pyGPUreg/shaders/fft_inversion_permutation_single.glsl
pyGPUreg/shaders/fft_phase_correlation.glsl
pyGPUreg/shaders/fft_phase_correlation_single.glsl
pyGPUreg/shaders/fft_single.glsl
pyGPUreg/shaders/resample_image.glsl