Metadata-Version: 2.1
Name: pyGPUreg
Version: 0.1.5
Summary: GPU-accelerated image registration. github.com/bionanopatterning/pyGPUreg
Home-page: UNKNOWN
Author: Mart G.F. Last
Author-email: m.g.f.last@lumc.nl
License: GPLv3
Platform: UNKNOWN
License-File: LICENSE.txt
